io_scene_3ds/__init__.py
io_scene_3ds/export_3ds.py
io_scene_3ds/import_3ds.py
io_scene_3ds-2.8.5.dist-info/METADATA
io_scene_3ds-2.8.5.dist-info/WHEEL
io_scene_3ds-2.8.5.dist-info/RECORD
