Metadata-Version: 2.1
Name: io_scene_3ds
Version: 2.8.5
Summary: Autodesk 3D Studio Blender Extension
Home-page: https://www.nrgsille.com/
License: GPL-2.0-or-later
Author: Sebastian Schrand
Maintainer: Sebastian Sille
Maintainer-email: getmore@nrgsille.com
Requires-Python: >=3,<4
Classifier: License :: OSI Approved :: GNU General Public License v2 or later (GPLv2+)
Classifier: Programming Language :: Python :: 3
Classifier: Programming Language :: Python :: 3.4
Classifier: Programming Language :: Python :: 3.5
Classifier: Programming Language :: Python :: 3.6
Classifier: Programming Language :: Python :: 3.7
Classifier: Programming Language :: Python :: 3.8
Classifier: Programming Language :: Python :: 3.9
Classifier: Programming Language :: Python :: 3.10
Classifier: Programming Language :: Python :: 3.11
Classifier: Programming Language :: Python :: 3.12
Project-URL: Repository, https://github.com/nrgsille76/blender-io-addons
